gh_action_docs/__init__.py
gh_action_docs/app.py
gh_action_docs-1.1.2.dist-info/entry_points.txt
gh_action_docs-1.1.2.dist-info/LICENSE
gh_action_docs-1.1.2.dist-info/WHEEL
gh_action_docs-1.1.2.dist-info/METADATA
gh_action_docs-1.1.2.dist-info/RECORD
